imio.behavior.teleservices-1.0.5-py2.7-nspkg.pth
imio/behavior/teleservices/__init__.py
imio/behavior/teleservices/config.py
imio/behavior/teleservices/configure.zcml
imio/behavior/teleservices/interfaces.py
imio/behavior/teleservices/permissions.zcml
imio/behavior/teleservices/setuphandlers.py
imio/behavior/teleservices/testing.py
imio/behavior/teleservices/utils.py
imio/behavior/teleservices/vocabularies.py
imio/behavior/teleservices/widgets.py
imio/behavior/teleservices/behaviors/__init__.py
imio/behavior/teleservices/behaviors/configure.zcml
imio/behavior/teleservices/behaviors/ts_procedure.py
imio/behavior/teleservices/browser/__init__.py
imio/behavior/teleservices/browser/configure.zcml
imio/behavior/teleservices/browser/controlpanel.py
imio/behavior/teleservices/browser/procedures_viewlet.py
imio/behavior/teleservices/browser/ts_procedure.py
imio/behavior/teleservices/browser/overrides/.gitkeep
imio/behavior/teleservices/browser/static/.gitkeep
imio/behavior/teleservices/browser/templates/bad_config.pt
imio/behavior/teleservices/browser/templates/no_config.pt
imio/behavior/teleservices/browser/templates/procedures_viewlet.pt
imio/behavior/teleservices/browser/templates/select_display.pt
imio/behavior/teleservices/locales/README.rst
imio/behavior/teleservices/locales/__init__.py
imio/behavior/teleservices/locales/imio.behavior.teleservices.pot
imio/behavior/teleservices/locales/update.py
imio/behavior/teleservices/locales/update.sh
imio/behavior/teleservices/locales/en/LC_MESSAGES/imio.behavior.teleservices.po
imio/behavior/teleservices/locales/fr/LC_MESSAGES/imio.behavior.teleservices.po
imio/behavior/teleservices/profiles/default/browserlayer.xml
imio/behavior/teleservices/profiles/default/catalog.xml
imio/behavior/teleservices/profiles/default/controlpanel.xml
imio/behavior/teleservices/profiles/default/import_steps.xml
imio/behavior/teleservices/profiles/default/metadata.xml
imio.behavior.teleservices-1.0.5.dist-info/DESCRIPTION.rst
imio.behavior.teleservices-1.0.5.dist-info/METADATA
imio.behavior.teleservices-1.0.5.dist-info/RECORD
imio.behavior.teleservices-1.0.5.dist-info/WHEEL
imio.behavior.teleservices-1.0.5.dist-info/entry_points.txt
imio.behavior.teleservices-1.0.5.dist-info/metadata.json
imio.behavior.teleservices-1.0.5.dist-info/namespace_packages.txt
imio.behavior.teleservices-1.0.5.dist-info/top_level.txt
