Metadata-Version: 2.0
Name: imio.behavior.teleservices
Version: 1.0.5
Summary: Plone behavior to get (and set) global E-Guichet/Teleservices configuration into a Plone Application. Expose E-Guichet procedures in a select field.
Home-page: https://github.com/collective/imio.behavior.teleservices
Author: Christophe Boulanger
Author-email: christophe.boulanger@imio.be
License: GPL version 2
Project-URL: Source, https://github.com/collective/imio.behavior.teleservices
Project-URL: Tracker, https://github.com/collective/imio.behavior.teleservices/issues
Project-URL: PyPI, https://pypi.python.org/pypi/imio.behavior.teleservices
Keywords: Python Plone
Platform: UNKNOWN
Classifier: Environment :: Web Environment
Classifier: Framework :: Plone
Classifier: Framework :: Plone :: Addon
Classifier: Framework :: Plone :: 4.3
Classifier: Programming Language :: Python
Classifier: Programming Language :: Python :: 2.7
Classifier: Operating System :: OS Independent
Classifier: License :: OSI Approved :: GNU General Public License v2 (GPLv2)
Requires-Python: ==2.7
Provides-Extra: test
Requires-Dist: setuptools
Requires-Dist: collective.z3cform.select2
Requires-Dist: z3c.jbot
Requires-Dist: Products.GenericSetup (>=1.8.2)
Requires-Dist: plone.api (>=1.8.4)
Requires-Dist: plone.restapi
Requires-Dist: plone.app.contenttypes
Requires-Dist: plone.app.dexterity
Requires-Dist: plone.app.referenceablebehavior
Requires-Dist: plone.app.relationfield
Requires-Dist: plone.app.lockingbehavior
Requires-Dist: plone.schema
Requires-Dist: requests
Provides-Extra: test
Requires-Dist: plone.app.testing; extra == 'test'
Requires-Dist: plone.testing (>=5.0.0); extra == 'test'
Requires-Dist: plone.app.robotframework[debug]; extra == 'test'
